Metadata-Version: 2.1
Name: print-logger
Version: 1.0.3
Summary: Print Logger Python print with strict structure
Home-page: https://github.com/xuanhuan95/print_log
Author: Huan Nguyen
Author-email: nguyenxuanhuan.95@gmail.com
License: MIT
Keywords: PYTHON,PRINT,LOGGING
Platform: UNKNOWN
Classifier: Development Status :: 5 - Production/Stable
Classifier: Intended Audience :: Developers
Classifier: Topic :: Software Development :: Build Tools
Classifier: License :: OSI Approved :: MIT License
Classifier: Programming Language :: Python :: 3.8
License-File: LICENSE.txt
